balue/__init__.py
balue/encryptor.py
balue-0.1.0.dist-info/LICENSE
balue-0.1.0.dist-info/METADATA
balue-0.1.0.dist-info/WHEEL
balue-0.1.0.dist-info/RECORD
