Metadata-Version: 2.1
Name: balue
Version: 0.1.0
Summary: Explore the intricacies of cryptographic techniques with Balu, a Python library implementing a sophisticated multi-layer encryption system. Balu combines substitution, permutation, and XOR ciphers to offer a customizable and educational approach to data security.
License: Apache-2.0
Keywords: Balue,ComplexEncryptor,Encryption,Decryption,Substitution Cipher,Permutation Cipher,XOR Cipher,Cryptography,Encryption Algorithm,Data Security,Python Encryption,Multi-layer Encryption,Secure Communication,Python Cryptography,Hashing,SHA-256,Byte Shuffling,Cipher Techniques,Symmetric Encryption,Educational Cryptography,Encryption Example,Python Package,Poetry Package,Secure Key,Message Encryption,Custom Encryption,Encryption Project,Python Security,Encryption Techniques,Open Source Encr
Author: aliezzahn
Author-email: alireza.h@laqira.io
Requires-Python: >=3.11,<4.0
Classifier: License :: OSI Approved :: Apache Software License
Classifier: Programming Language :: Python :: 3
Classifier: Programming Language :: Python :: 3.11
Classifier: Programming Language :: Python :: 3.12
